photo4d/Class_pcl_processing.py
photo4d/Class_photo4D.py
photo4d/Detect_Sift.py
photo4d/Image_utils.py
photo4d/Process.py
photo4d/Utils.py
photo4d/XML_utils.py
photo4d/__init__.py
photo4d/__version__.py
photo4d/pdal_python_filter.py
photo4d-0.2.2.dist-info/LICENSE
photo4d-0.2.2.dist-info/METADATA
photo4d-0.2.2.dist-info/WHEEL
photo4d-0.2.2.dist-info/top_level.txt
photo4d-0.2.2.dist-info/RECORD
