Metadata-Version: 2.1
Name: photo4d
Version: 0.2.2
Summary: Open source project to perform time-lapse photogrammetry
Home-page: https://github.com/ArcticSnow/photo4D
Author: S. Filhol, A. Perret, G. Sutter, and L. Girod
Author-email: simon.filhol@geo.uio.no
License: MIT
Platform: UNKNOWN
Classifier: License :: OSI Approved :: MIT License
Classifier: Programming Language :: Python
Classifier: Programming Language :: Python :: 3
Classifier: Programming Language :: Python :: 3.6
Classifier: Programming Language :: Python :: Implementation :: CPython
Classifier: Programming Language :: Python :: Implementation :: PyPy
Requires-Python: >=3.6.0
Requires-Dist: lxml
Requires-Dist: pandas
Requires-Dist: numpy
Requires-Dist: matplotlib
Requires-Dist: opencv-python
Requires-Dist: pillow
Requires-Dist: glob
Provides-Extra: required_to_use_the_class_pcl_process_
Requires-Dist: pdal ; extra == 'required_to_use_the_class_pcl_process_'
Requires-Dist: json ; extra == 'required_to_use_the_class_pcl_process_'
